setup.py
workmail20/__init__.py
workmail20/pirichain.py
pirichain_api_workmail20-1.0.1.dist-info/METADATA
pirichain_api_workmail20-1.0.1.dist-info/WHEEL
pirichain_api_workmail20-1.0.1.dist-info/licenses/LICENSE
pirichain_api_workmail20-1.0.1.dist-info/RECORD
