Metadata-Version: 2.1
Name: pirichain_api_workmail20
Version: 1.0.1
Summary: Package for base Pirichain API calls
Project-URL: Homepage, https://github.com/workmail20/pirichain-api-python
Project-URL: Bug Tracker, https://github.com/workmail20/pirichain-api-python/issues
Author-email: workmail20 <work_mail20@protonmail.com>
License-File: LICENSE
Classifier: License :: OSI Approved :: MIT License
Classifier: Operating System :: OS Independent
Classifier: Programming Language :: Python :: 3
Requires-Python: >=3.7
